FloorplanAnalytics/__init__.py
FloorplanAnalytics/analytics.py
FloorplanAnalytics/lib/Floodfill.py
FloorplanAnalytics/lib/GeodesicDistanceMulti.py
FloorplanAnalytics/lib/GeodesicRange.py
FloorplanAnalytics/lib/GeodesicRangeUnlimited.py
FloorplanAnalytics/lib/RaycastDistance.py
FloorplanAnalytics/lib/SignedDistance.py
FloorplanAnalytics/lib/StepDepth.py
FloorplanAnalytics/lib/StepDepthIsovist.py
FloorplanAnalytics/lib/VisibleArea.py
FloorplanAnalytics/lib/VisibleObstacle.py
FloorplanAnalytics/lib/__init__.py
FloorplanAnalytics/lib/helper/Colorhelper.py
FloorplanAnalytics/lib/helper/Helperfunctions.py
FloorplanAnalytics/lib/helper/__init__.py
floorplananalytics-0.0.4.dist-info/licenses/LICENSE
floorplananalytics-0.0.4.dist-info/METADATA
floorplananalytics-0.0.4.dist-info/WHEEL
floorplananalytics-0.0.4.dist-info/top_level.txt
floorplananalytics-0.0.4.dist-info/RECORD
