Metadata-Version: 2.4
Name: FloorplanAnalytics
Version: 0.0.4
Summary: A library to analyze floor plans with common space syntax metrics.
Author-email: Christoph Geiger <christoph.r.geiger@gmail.com>
Maintainer-email: Christoph Geiger <christoph.r.geiger@gmail.com>
License:                     GNU GENERAL PUBLIC LICENSE
Project-URL: Source, https://github.com/Cybernaut0815/FloorplanAnalytics
Keywords: architectural computation,computational design,scientific computation,spatial analytics,space syntax,urban analytics
Classifier: Development Status :: 3 - Alpha
Classifier: Intended Audience :: Science/Research
Classifier: Topic :: Software Development :: Build Tools
Classifier: License :: OSI Approved :: GNU General Public License v3 (GPLv3)
Classifier: Programming Language :: Python :: 3.9
Classifier: Programming Language :: Python :: 3.10
Classifier: Programming Language :: Python :: 3.11
Classifier: Programming Language :: Python :: 3.12
Classifier: Programming Language :: Python :: 3.13
Requires-Python: >=3.9
License-File: LICENSE
Requires-Dist: matplotlib~=3.10.8
Requires-Dist: numpy~=2.3.5
Requires-Dist: pillow~=12.0.0
Requires-Dist: scipy~=1.16.3
Requires-Dist: numba-cuda~=0.22.1
Dynamic: license-file
